kuramoto_chimera/__init__.py
kuramoto_chimera-0.0.2.dist-info/LICENSE
kuramoto_chimera-0.0.2.dist-info/METADATA
kuramoto_chimera-0.0.2.dist-info/WHEEL
kuramoto_chimera-0.0.2.dist-info/top_level.txt
kuramoto_chimera-0.0.2.dist-info/RECORD
