Metadata-Version: 2.1
Name: kuramoto_chimera
Version: 0.0.2
Summary: Chimera states in nonlocally-coupled phase oscillators
Home-page: https://github.com/fkemeth/kuramoto_chimera
Author: Felix P. Kemeth
Author-email: felix@kemeth.de
License: UNKNOWN
Project-URL: Bug Tracker, https://github.com/fkemeth/kuramoto_chimera/issues
Platform: UNKNOWN
Classifier: Programming Language :: Python :: 3
Classifier: License :: OSI Approved :: GNU General Public License v3 (GPLv3)
Classifier: Operating System :: OS Independent
Requires-Python: >=3.6
License-File: LICENSE
